.gitignore
README
bootstrap.py
buildout.cfg
setup.py
wsgi_cache/__init__.py
wsgi_cache.egg-info/PKG-INFO
wsgi_cache.egg-info/SOURCES.txt
wsgi_cache.egg-info/dependency_links.txt
wsgi_cache.egg-info/entry_points.txt
wsgi_cache.egg-info/requires.txt
wsgi_cache.egg-info/top_level.txt
wsgi_cache/tests/__init__.py
wsgi_cache/tests/app.py
wsgi_cache/tests/test_app.py