Metadata-Version: 1.0
Name: wsgi-cache
Version: 0.2.3
Summary: WSGI middleware for caching responses to disk.
Home-page: UNKNOWN
Author: Nathan R. Yergler
Author-email: nathan@yergler.net
License: MIT
Platform: UNKNOWN
